scarches/__init__.py
scarches/dataset/__init__.py
scarches/dataset/mars/__init__.py
scarches/dataset/mars/meta_anndata.py
scarches/dataset/scvi/__init__.py
scarches/dataset/scvi/annotation_data_loader.py
scarches/dataset/scvi/scvi_data_loader.py
scarches/dataset/scvi/total_data_loader.py
scarches/dataset/trvae/__init__.py
scarches/dataset/trvae/_utils.py
scarches/dataset/trvae/anndata.py
scarches/dataset/trvae/data_handling.py
scarches/metrics/__init__.py
scarches/metrics/metrics.py
scarches/models/__init__.py
scarches/models/mars/__init__.py
scarches/models/mars/activations.py
scarches/models/mars/losses.py
scarches/models/mars/mars.py
scarches/models/scvi/__init__.py
scarches/models/scvi/classifier.py
scarches/models/scvi/scanvi.py
scarches/models/scvi/scvi.py
scarches/models/scvi/totalvi.py
scarches/models/scvi/_base/__init__.py
scarches/models/trvae/__init__.py
scarches/models/trvae/_utils.py
scarches/models/trvae/activations.py
scarches/models/trvae/losses.py
scarches/models/trvae/modules.py
scarches/models/trvae/trvae.py
scarches/plotting/__init__.py
scarches/plotting/_alluvial.py
scarches/plotting/sankey.py
scarches/plotting/scvi_eval.py
scarches/surgery/__init__.py
scarches/surgery/mars.py
scarches/surgery/scvi.py
scarches/surgery/trvae.py
scarches/trainers/__init__.py
scarches/trainers/mars/__init__.py
scarches/trainers/mars/_utils.py
scarches/trainers/mars/mars_meta_trainer.py
scarches/trainers/mars/meta.py
scarches/trainers/mars/unsupervised.py
scarches/trainers/scvi/__init__.py
scarches/trainers/scvi/annotation.py
scarches/trainers/scvi/inference.py
scarches/trainers/scvi/total_inference.py
scarches/trainers/scvi/trainer.py
scarches/trainers/trvae/__init__.py
scarches/trainers/trvae/_utils.py
scarches/trainers/trvae/trainer.py
scarches/trainers/trvae/unsupervised.py
scarches/utils/__init__.py
scarches/utils/monitor.py
scarches/utils/scvi/__init__.py
scarches/utils/scvi/_constants.py
scarches/utils/scvi/_settings.py
scarchest/__init__.py
scArchest-0.0.1.dist-info/METADATA
scArchest-0.0.1.dist-info/WHEEL
scArchest-0.0.1.dist-info/top_level.txt
scArchest-0.0.1.dist-info/RECORD
