Metadata-Version: 2.1
Name: scArchest
Version: 0.0.1
Summary: Transfer learning with Architecture Surgery on Single-cell data
Home-page: https://github.com/theislab/scarchesp
Author: Marco Wagenstetter, Mohsen Naghipourfar, Mohammad Lotfollahi
Author-email: cottoneyejoe.server@gmail.com, naghipourfar@ce.sharif.edu, mohammad.lotfollahi@helmholtz-muenchen.de
License: MIT
Platform: UNKNOWN
Classifier: Programming Language :: Python :: 3.6
Classifier: Programming Language :: Python :: 3.7
Classifier: Environment :: Console
Classifier: Framework :: Jupyter
Classifier: Intended Audience :: Developers
Classifier: Intended Audience :: Science/Research
Classifier: License :: OSI Approved :: MIT License
Classifier: Natural Language :: English
Classifier: Operating System :: MacOS :: MacOS X
Classifier: Operating System :: Microsoft :: Windows
Classifier: Operating System :: POSIX :: Linux
Requires-Dist: scanpy (~=1.6.0)
Requires-Dist: torch (~=1.6.0)
Requires-Dist: numpy (~=1.19.2)
Requires-Dist: scipy (~=1.5.2)
Requires-Dist: scikit-learn (~=0.23.2)
Requires-Dist: matplotlib (~=3.3.1)
Requires-Dist: anndata (~=0.7.4)
Requires-Dist: pandas (~=1.1.2)
Requires-Dist: h5py (~=2.10.0)
Requires-Dist: tqdm (~=4.49.0)
Requires-Dist: scvi-tools
Requires-Dist: sfaira
